sai_isaac/__init__.py
sai_isaac/cobotstack/__init__.py
sai_isaac/cobotstack/cobot_config.py
sai_isaac/cobotstack/cobot_stack_env.py
sai_isaac/cobotstack/assets/config.yaml
sai_isaac/cobotstack/assets/flattened_visual_jetcobot.usd
sai_isaac/cobotstack/assets/configuration/jetcobot_base.usd
sai_isaac/cobotstack/assets/configuration/jetcobot_physics.usd
sai_isaac/cobotstack/assets/configuration/jetcobot_sensor.usd
sai_isaac/franka_golf/__init__.py
sai_isaac/franka_golf/franka_golf_direct_env.py
sai_isaac/franka_golf/franka_golf_env.py
sai_isaac/franka_golf/assets/golf_club.usda
sai_isaac/franka_golf/assets/golf_course.usd
sai_isaac/franka_golf/mdp/__init__.py
sai_isaac/franka_golf/mdp/events.py
sai_isaac/franka_golf/mdp/observations.py
sai_isaac/franka_golf/mdp/rewards.py
sai_isaac/franka_golf/mdp/terminations.py
sai_isaac/utils/common.py
sai_isaac-0.0.7.dist-info/METADATA
sai_isaac-0.0.7.dist-info/WHEEL
sai_isaac-0.0.7.dist-info/licenses/LICENSE
sai_isaac-0.0.7.dist-info/RECORD
