Metadata-Version: 2.4
Name: sai-isaac
Version: 0.0.7
Summary: A collection of isaac-sim based robotics environments for the SAI platform.
Author-email: ArenaX Labs <research@competesai.com>
License: MIT
License-File: LICENSE
Requires-Python: >=3.10
Requires-Dist: gymnasium>=1.0.0
Requires-Dist: isaaclab[all,isaacsim]==2.0.2; sys_platform == 'linux'
Requires-Dist: numpy==1.26.0
Requires-Dist: torch==2.5.1
